microhtml.py
py_microhtml-0.1.dist-info/LICENSE
py_microhtml-0.1.dist-info/METADATA
py_microhtml-0.1.dist-info/WHEEL
py_microhtml-0.1.dist-info/top_level.txt
py_microhtml-0.1.dist-info/RECORD
