Metadata-Version: 2.1
Name: py-microhtml
Version: 0.1
Summary: Minimalistic HTML builder for Python 3.6+ with compact syntax
Home-page: https://github.com/elonen/py_microhtml
Author: Jarno Elonen
Author-email: elonen@iki.fi
License: UNKNOWN
Platform: UNKNOWN
Classifier: Programming Language :: Python :: 3.6
Classifier: License :: OSI Approved :: MIT License
Classifier: Operating System :: OS Independent
Classifier: Topic :: Text Processing :: Markup :: HTML
Classifier: Topic :: Internet :: WWW/HTTP :: Dynamic Content
Classifier: Topic :: Software Development :: Libraries :: Python Modules
Requires-Dist: pytidylib
